.coveragerc
.yamllint
CHANGELOG.md
COPYING
MANIFEST.in
Makefile
README.md
VERSION
requirements.txt
setup.py
bin/ansible
bin/ansible-connection
bin/ansible-console
bin/ansible-doc
bin/ansible-galaxy
bin/ansible-playbook
bin/ansible-pull
bin/ansible-vault
contrib/README.md
contrib/inventory/abiquo.ini
contrib/inventory/abiquo.py
contrib/inventory/apache-libcloud.py
contrib/inventory/apstra_aos.ini
contrib/inventory/apstra_aos.py
contrib/inventory/azure_rm.ini
contrib/inventory/azure_rm.py
contrib/inventory/brook.ini
contrib/inventory/brook.py
contrib/inventory/cloudforms.ini
contrib/inventory/cloudforms.py
contrib/inventory/cloudstack.ini
contrib/inventory/cloudstack.py
contrib/inventory/cobbler.ini
contrib/inventory/cobbler.py
contrib/inventory/collins.ini
contrib/inventory/collins.py
contrib/inventory/consul.ini
contrib/inventory/consul_io.py
contrib/inventory/digital_ocean.ini
contrib/inventory/digital_ocean.py
contrib/inventory/docker.py
contrib/inventory/docker.yml
contrib/inventory/ec2.ini
contrib/inventory/ec2.py
contrib/inventory/fleet.py
contrib/inventory/foreman.ini
contrib/inventory/foreman.py
contrib/inventory/freeipa.py
contrib/inventory/gce.ini
contrib/inventory/gce.py
contrib/inventory/jail.py
contrib/inventory/landscape.py
contrib/inventory/libcloud.ini
contrib/inventory/libvirt_lxc.py
contrib/inventory/linode.ini
contrib/inventory/linode.py
contrib/inventory/lxc_inventory.py
contrib/inventory/mdt.ini
contrib/inventory/mdt_dynamic_inventory.py
contrib/inventory/nagios_livestatus.ini
contrib/inventory/nagios_livestatus.py
contrib/inventory/nagios_ndo.ini
contrib/inventory/nagios_ndo.py
contrib/inventory/nova.ini
contrib/inventory/nova.py
contrib/inventory/nsot.py
contrib/inventory/nsot.yaml
contrib/inventory/openshift.py
contrib/inventory/openstack.py
contrib/inventory/openstack.yml
contrib/inventory/openvz.py
contrib/inventory/ovirt.ini
contrib/inventory/ovirt.py
contrib/inventory/ovirt4.py
contrib/inventory/packet_net.ini
lib/ansible.egg-info/PKG-INFO
lib/ansible.egg-info/SOURCES.txt
lib/ansible.egg-info/dependency_links.txt
lib/ansible.egg-info/requires.txt
lib/ansible.egg-info/top_level.txt
